<?xml version="1.0" encoding="UTF-8"?><?xml-stylesheet type='text/xsl' href='_UpgradeReport_Files/UpgradeReport.xslt'?><UpgradeLog>
<Properties><Property Name="Solution" Value="18-bugz">
</Property><Property Name="Solution File" Value="C:\Users\Michael Bekesz\Desktop\School\School 07-09\School 09\Spring09\CS161ObjectOriented\PublicFolder\18-bugz\18-bugz.sln">
</Property><Property Name="Date" Value="Tuesday, May 01, 2012">
</Property><Property Name="Time" Value="22:04:40 PM">
</Property></Properties><Event ErrorLevel="3" Project="18-bugz" Source="18-bugz.vcproj" Description="No Conversion Required">
</Event></UpgradeLog>